cli2telegram/__init__.py
cli2telegram/cli.py
cli2telegram/config.py
cli2telegram/const.py
cli2telegram/daemon.py
cli2telegram/util.py
cli2telegram-2.0.1.dist-info/LICENSE
cli2telegram-2.0.1.dist-info/METADATA
cli2telegram-2.0.1.dist-info/WHEEL
cli2telegram-2.0.1.dist-info/entry_points.txt
cli2telegram-2.0.1.dist-info/RECORD
