Metadata-Version: 2.1
Name: cli2telegram
Version: 2.0.1
Summary: Small utility to send Telegram messages from the CLI.
Home-page: https://github.com/markusressel/cli2telegram
License: AGPL-3.0-or-later
Keywords: cli,telegram,notification
Author: Markus Ressel
Author-email: mail@markusressel.de
Requires-Python: >=3.7,<4.0
Classifier: Development Status :: 5 - Production/Stable
Classifier: License :: OSI Approved :: GNU Affero General Public License v3 or later (AGPLv3+)
Classifier: Programming Language :: Python :: 3
Classifier: Programming Language :: Python :: 3.7
Classifier: Programming Language :: Python :: 3.8
Classifier: Programming Language :: Python :: 3.9
Classifier: Programming Language :: Python :: 3.10
Classifier: Programming Language :: Python :: 3.11
Classifier: Programming Language :: Python :: 3
Classifier: Programming Language :: Python :: 3 :: Only
Classifier: Programming Language :: Python :: 3.10
Classifier: Programming Language :: Python :: 3.7
Classifier: Programming Language :: Python :: 3.8
Classifier: Programming Language :: Python :: 3.9
Requires-Dist: aiofiles
Requires-Dist: click
Requires-Dist: container-app-conf
Requires-Dist: emoji
Requires-Dist: python-telegram-bot
Project-URL: Repository, https://github.com/markusressel/cli2telegram
